genesis/__init__.py
genesis/__main__.py
genesis/channel.py
genesis/cli/__init__.py
genesis/cli/consumer.py
genesis/cli/discover.py
genesis/cli/exceptions.py
genesis/cli/outbound.py
genesis/cli/utils.py
genesis/cli/watcher.py
genesis/consumer.py
genesis/exceptions.py
genesis/group/__init__.py
genesis/group/load_balancer.py
genesis/group/ring.py
genesis/inbound.py
genesis/logger.py
genesis/outbound.py
genesis/parser.py
genesis/protocol.py
genesis/types.py
genesis-2026.1.26.dist-info/METADATA
genesis-2026.1.26.dist-info/WHEEL
genesis-2026.1.26.dist-info/entry_points.txt
genesis-2026.1.26.dist-info/licenses/LICENSE.md
genesis-2026.1.26.dist-info/RECORD
