Metadata-Version: 2.4
Name: genesis
Version: 2026.1.26
Summary: Async Python library for FreeSWITCH Event Socket Layer (ESL) - Build high-performance telephony applications with asyncio
License: MIT
License-File: LICENSE.md
Keywords: freeswitch,esl,event-socket,telephony,voip,asyncio,async,pbx,ivr,sip,webrtc
Author: Vitor
Author-email: vitor.hov@gmail.com
Requires-Python: >=3.10,<3.13
Classifier: Development Status :: 5 - Production/Stable
Classifier: Framework :: AsyncIO
Classifier: Intended Audience :: Developers
Classifier: Intended Audience :: Information Technology
Classifier: Intended Audience :: Telecommunications Industry
Classifier: License :: OSI Approved :: MIT License
Classifier: Operating System :: OS Independent
Classifier: Programming Language :: Python :: 3
Classifier: Programming Language :: Python :: 3.10
Classifier: Programming Language :: Python :: 3.11
Classifier: Programming Language :: Python :: 3.12
Classifier: Programming Language :: Python :: 3 :: Only
Classifier: Topic :: Communications :: Telephony
Classifier: Topic :: Internet
Classifier: Topic :: Software Development :: Libraries :: Python Modules
Provides-Extra: redis
Requires-Dist: opentelemetry-api (>=1.39.1,<2.0.0)
Requires-Dist: opentelemetry-exporter-prometheus (>=0.60b1,<0.61)
Requires-Dist: redis (>=5.0.0,<6.0.0) ; extra == "redis"
Requires-Dist: rich (>=13.7.1,<14.0.0)
Requires-Dist: typer (>=0.12.3,<0.13.0)
Requires-Dist: watchdog (>=4.0.2,<5.0.0)
Project-URL: Bug Tracker, https://github.com/Otoru/Genesis/issues
Project-URL: Changelog, https://github.com/Otoru/Genesis/releases
Project-URL: Documentation, https://otoru.github.io/Genesis/
Project-URL: Homepage, https://github.com/Otoru/Genesis#readme
Project-URL: Repository, https://github.com/Otoru/Genesis
Project-URL: Source Code, https://github.com/Otoru/Genesis
